draw.py
setup.py
SampleDraw.egg-info/PKG-INFO
SampleDraw.egg-info/SOURCES.txt
SampleDraw.egg-info/dependency_links.txt
SampleDraw.egg-info/top_level.txt