Metadata-Version: 2.1
Name: SampleDraw
Version: 1.0.0
Summary: 一个用Tkinter写的、简易的画图工具
Home-page: UNKNOWN
Author: Eno
Author-email: 
License: UNKNOWN
Platform: UNKNOWN
